exal/__init__.py
exal/helper.py
exal/drivers/__init__.py
exal/drivers/basedriver.py
exal/drivers/comtypedriver.py
exal/drivers/openpyxldriver.py
exal/drivers/win32comdriver.py
exal/drivers/xlwingsdriver.py
exal-1.0.2.dev0.dist-info/METADATA
exal-1.0.2.dev0.dist-info/RECORD
exal-1.0.2.dev0.dist-info/WHEEL
exal-1.0.2.dev0.dist-info/entry_points.txt
exal-1.0.2.dev0.dist-info/top_level.txt
exal-1.0.2.dev0.dist-info/zip-safe
